itk/Configuration/MeshNoiseConfig.py
itk/Configuration/MeshNoise_snake_case.py
itk/MeshNoisePython.py
itk/_MeshNoisePython.abi3.so
itk/itkAdditiveGaussianNoiseMeshFilterPython.py
itk/itkAdditiveGaussianNoiseQuadEdgeMeshFilterPython.py
itk_meshnoise-1.0.0.dist-info/METADATA
itk_meshnoise-1.0.0.dist-info/WHEEL
itk_meshnoise-1.0.0.dist-info/entry_points.txt
itk_meshnoise-1.0.0.dist-info/licenses/LICENSE
itk_meshnoise-1.0.0.dist-info/RECORD
